{
  "rows": [
    {
      "freq": 0.45,
      "freq_label": "0.45",
      "freq_band": 1.0,
      "ingress": {
        "metric": -3.7679427657500644,
        "stderr": 3.5340450095276776,
        "n_used": 8
      },
      "egress": {
        "metric": -2.602895571648224,
        "stderr": 3.827995948868465,
        "n_used": 8
      },
      "combined": {
        "metric": -6.370838337398288,
        "stderr": 5.400124638421828,
        "n_used": 16
      }
    },
    {
      "freq": 0.7,
      "freq_label": "0.7",
      "freq_band": 2.0,
      "ingress": {
        "metric": 0.4968431618205822,
        "stderr": 2.3071878197584788,
        "n_used": 7
      },
      "egress": {
        "metric": 1.2236187235552303,
        "stderr": 1.4215845831396556,
        "n_used": 8
      },
      "combined": {
        "metric": 1.7204618853758125,
        "stderr": 2.8240619718143702,
        "n_used": 15
      }
    },
    {
      "freq": 0.9,
      "freq_label": "0.9",
      "freq_band": 3.0,
      "ingress": {
        "metric": -5.061357770500594,
        "stderr": 1.6581952228750774,
        "n_used": 8
      },
      "egress": {
        "metric": 4.63518007103478,
        "stderr": 1.5675588415651018,
        "n_used": 8
      },
      "combined": {
        "metric": -0.4261776994658142,
        "stderr": 3.3298530398238557,
        "n_used": 16
      }
    },
    {
      "freq": 1.31,
      "freq_label": "1.31",
      "freq_band": 4.0,
      "ingress": {
        "metric": -4.985319590672907,
        "stderr": 1.4115040495987856,
        "n_used": 9
      },
      "egress": {
        "metric": 1.2098042409289254,
        "stderr": 1.492144396695287,
        "n_used": 8
      },
      "combined": {
        "metric": -3.7755153497439813,
        "stderr": 2.5468586857817517,
        "n_used": 17
      }
    },
    {
      "freq": 2.2,
      "freq_label": "2.2",
      "freq_band": 5.0,
      "ingress": {
        "metric": -0.8086487541198655,
        "stderr": 1.359723725260585,
        "n_used": 8
      },
      "egress": {
        "metric": 0.2697862689514426,
        "stderr": 0.4127535605433636,
        "n_used": 8
      },
      "combined": {
        "metric": -0.5388624851684229,
        "stderr": 1.4938505669013629,
        "n_used": 16
      }
    },
    {
      "freq": 3.93,
      "freq_label": "3.93",
      "freq_band": 6.0,
      "ingress": {
        "metric": 1.2601659052540735,
        "stderr": 1.6292518097858042,
        "n_used": 7
      },
      "egress": {
        "metric": 1.181185816438811,
        "stderr": 1.5297934186371906,
        "n_used": 6
      },
      "combined": {
        "metric": 2.4413517216928846,
        "stderr": 2.3349075657977645,
        "n_used": 13
      }
    },
    {
      "freq": 4.7,
      "freq_label": "4.7",
      "freq_band": 7.0,
      "ingress": {
        "metric": 1.4134635060112246,
        "stderr": 1.2134161721875785,
        "n_used": 7
      },
      "egress": {
        "metric": -1.1959791868885545,
        "stderr": 0.7272581606840498,
        "n_used": 8
      },
      "combined": {
        "metric": 0.2174843191226703,
        "stderr": 1.6117501392771756,
        "n_used": 15
      }
    },
    {
      "freq": 6.55,
      "freq_label": "6.55",
      "freq_band": 8.0,
      "ingress": {
        "metric": -1.133243866950727,
        "stderr": 1.9936559530971794,
        "n_used": 8
      },
      "egress": {
        "metric": 1.411635625102516,
        "stderr": 1.678552959266645,
        "n_used": 11
      },
      "combined": {
        "metric": 0.2783917581517894,
        "stderr": 2.749437626082767,
        "n_used": 19
      }
    },
    {
      "freq": 9.18,
      "freq_label": "9.18",
      "freq_band": 9.0,
      "ingress": {
        "metric": -2.3603238361430865,
        "stderr": 1.4615386906187684,
        "n_used": 6
      },
      "egress": {
        "metric": 0.3323923642263835,
        "stderr": 0.9192304220506233,
        "n_used": 6
      },
      "combined": {
        "metric": -2.027931471916703,
        "stderr": 1.957820826752878,
        "n_used": 12
      }
    }
  ]
}